invenio_oarepo_dc/__init__.py
invenio_oarepo_dc/version.py
invenio_oarepo_dc/included_mappings/v6/dcterms-v1.0.0.json
invenio_oarepo_dc/included_mappings/v7/dcterms-v1.0.0.json
invenio_oarepo_dc/jsonschemas/__init__.py
invenio_oarepo_dc/jsonschemas/dcterms-v1.0.0.json
invenio_oarepo_dc/marshmallow/__init__.py
invenio_oarepo_dc-1.2.2.dist-info/LICENSE
invenio_oarepo_dc-1.2.2.dist-info/METADATA
invenio_oarepo_dc-1.2.2.dist-info/WHEEL
invenio_oarepo_dc-1.2.2.dist-info/entry_points.txt
invenio_oarepo_dc-1.2.2.dist-info/top_level.txt
invenio_oarepo_dc-1.2.2.dist-info/RECORD
